odoo8_addon_shopinvader_mailjet-8.0.1.0.0.99.dev2-py3.8-nspkg.pth
odoo_addons/shopinvader_mailjet/README.rst
odoo_addons/shopinvader_mailjet/__init__.py
odoo_addons/shopinvader_mailjet/__openerp__.py
odoo_addons/shopinvader_mailjet/models/__init__.py
odoo_addons/shopinvader_mailjet/models/email_template.py
odoo_addons/shopinvader_mailjet/models/mail.py
odoo_addons/shopinvader_mailjet/models/mail_server.py
odoo_addons/shopinvader_mailjet/models/notification.py
odoo_addons/shopinvader_mailjet/views/email_template_view.xml
odoo_addons/shopinvader_mailjet/views/mail_mail_view.xml
odoo_addons/shopinvader_mailjet/views/mail_server_view.xml
odoo8_addon_shopinvader_mailjet-8.0.1.0.0.99.dev2.dist-info/METADATA
odoo8_addon_shopinvader_mailjet-8.0.1.0.0.99.dev2.dist-info/WHEEL
odoo8_addon_shopinvader_mailjet-8.0.1.0.0.99.dev2.dist-info/namespace_packages.txt
odoo8_addon_shopinvader_mailjet-8.0.1.0.0.99.dev2.dist-info/top_level.txt
odoo8_addon_shopinvader_mailjet-8.0.1.0.0.99.dev2.dist-info/RECORD
